cosinnus_event/__init__.py
cosinnus_event/admin.py
cosinnus_event/apps.py
cosinnus_event/conf.py
cosinnus_event/cosinnus_app.py
cosinnus_event/cosinnus_notifications.py
cosinnus_event/dashboard.py
cosinnus_event/filters.py
cosinnus_event/forms.py
cosinnus_event/managers.py
cosinnus_event/models.py
cosinnus_event/notify.py
cosinnus_event/search_indexes.py
cosinnus_event/urls.py
cosinnus_event/views.py
cosinnus_event/locale/de/LC_MESSAGES/django.mo
cosinnus_event/locale/de/LC_MESSAGES/django.po
cosinnus_event/locale/en/LC_MESSAGES/django.mo
cosinnus_event/locale/en/LC_MESSAGES/django.po
cosinnus_event/locale/fr/LC_MESSAGES/django.mo
cosinnus_event/locale/fr/LC_MESSAGES/django.po
cosinnus_event/locale/ru/LC_MESSAGES/django.mo
cosinnus_event/locale/ru/LC_MESSAGES/django.po
cosinnus_event/locale/uk/LC_MESSAGES/django.mo
cosinnus_event/locale/uk/LC_MESSAGES/django.po
cosinnus_event/migrations/0001_initial.py
cosinnus_event/migrations/0002_auto_20151104_1711.py
cosinnus_event/migrations/0003_auto_20160125_1339.py
cosinnus_event/migrations/0004_auto_20160713_1852.py
cosinnus_event/migrations/0005_auto_20160727_1818.py
cosinnus_event/migrations/__init__.py
cosinnus_event/static/css/cosinnus_event/base.css
cosinnus_event/static/js/cosinnus_event/cosinnus_event.js
cosinnus_event/static/js/cosinnus_event/event_attendance.js
cosinnus_event/static/js/vendor/bootstrap.inline.js
cosinnus_event/templates/cosinnus_event/attached_events.html
cosinnus_event/templates/cosinnus_event/attached_object_select_pill.html
cosinnus_event/templates/cosinnus_event/base.html
cosinnus_event/templates/cosinnus_event/doodle_form.html
cosinnus_event/templates/cosinnus_event/doodle_list.html
cosinnus_event/templates/cosinnus_event/doodle_list_detailed_archived.html
cosinnus_event/templates/cosinnus_event/doodle_vote.html
cosinnus_event/templates/cosinnus_event/event_comments.html
cosinnus_event/templates/cosinnus_event/event_detail.html
cosinnus_event-0.6.dev20180515152253.dist-info/DESCRIPTION.rst
cosinnus_event-0.6.dev20180515152253.dist-info/METADATA
cosinnus_event-0.6.dev20180515152253.dist-info/RECORD
cosinnus_event-0.6.dev20180515152253.dist-info/WHEEL
cosinnus_event-0.6.dev20180515152253.dist-info/metadata.json
cosinnus_event-0.6.dev20180515152253.dist-info/top_level.txt
